karr_lab_aws_manager/__init__.py
karr_lab_aws_manager/__main__.py
karr_lab_aws_manager/_version.py
karr_lab_aws_manager/core.py
karr_lab_aws_manager/config/__init__.py
karr_lab_aws_manager/config/config.py
karr_lab_aws_manager/ec2/__init__.py
karr_lab_aws_manager/elasticsearch_kl/__init__.py
karr_lab_aws_manager/elasticsearch_kl/index_setting_file.py
karr_lab_aws_manager/elasticsearch_kl/query_builder.py
karr_lab_aws_manager/elasticsearch_kl/util.py
karr_lab_aws_manager/quilt3_kl/__init__.py
karr_lab_aws_manager/quilt3_kl/util.py
karr_lab_aws_manager/s3/__init__.py
karr_lab_aws_manager/s3/util.py
karr_lab_aws_manager-0.0.23.dist-info/LICENSE
karr_lab_aws_manager-0.0.23.dist-info/METADATA
karr_lab_aws_manager-0.0.23.dist-info/WHEEL
karr_lab_aws_manager-0.0.23.dist-info/entry_points.txt
karr_lab_aws_manager-0.0.23.dist-info/top_level.txt
karr_lab_aws_manager-0.0.23.dist-info/RECORD
